[
  {
    "hands": [
      [
        [
          429,
          358
        ],
        [
          450,
          338
        ],
        [
          469,
          315
        ],
        [
          482,
          293
        ],
        [
          495,
          276
        ],
        [
          441,
          291
        ],
        [
          444,
          261
        ],
        [
          445,
          239
        ],
        [
          449,
          0
        ],
        [
          422,
          294
        ],
        [
          417,
          257
        ],
        [
          410,
          237
        ],
        [
          378,
          0
        ],
        [
          407,
          302
        ],
        [
          394,
          271
        ],
        [
          386,
          253
        ],
        [
          379,
          238
        ],
        [
          395,
          316
        ],
        [
          378,
          300
        ],
        [
          369,
          290
        ],
        [
          359,
          279
        ]
      ]
    ],
    "frame_index": 0
  },
  {
    "hands": [
      [
        [
          425,
          367
        ],
        [
          446,
          348
        ],
        [
          466,
          326
        ],
        [
          479,
          303
        ],
        [
          494,
          286
        ],
        [
          438,
          305
        ],
        [
          442,
          274
        ],
        [
          445,
          252
        ],
        [
          448,
          0
        ],
        [
          420,
          310
        ],
        [
          418,
          273
        ],
        [
          414,
          250
        ],
        [
          409,
          0
        ],
        [
          405,
          319
        ],
        [
          396,
          289
        ],
        [
          389,
          270
        ],
        [
          384,
          254
        ],
        [
          393,
          334
        ],
        [
          378,
          316
        ],
        [
          370,
          308
        ],
        [
          363,
          300
        ]
      ]
    ],
    "frame_index": 1
  },
  {
    "hands": [
      [
        [
          425,
          368
        ],
        [
          446,
          348
        ],
        [
          466,
          326
        ],
        [
          480,
          303
        ],
        [
          494,
          286
        ],
        [
          438,
          305
        ],
        [
          442,
          275
        ],
        [
          444,
          252
        ],
        [
          447,
          0
        ],
        [
          420,
          310
        ],
        [
          418,
          276
        ],
        [
          414,
          250
        ],
        [
          408,
          0
        ],
        [
          406,
          319
        ],
        [
          396,
          290
        ],
        [
          389,
          270
        ],
        [
          384,
          254
        ],
        [
          394,
          334
        ],
        [
          378,
          316
        ],
        [
          370,
          308
        ],
        [
          363,
          299
        ]
      ]
    ],
    "frame_index": 2
  },
  {
    "hands": [
      [
        [
          417,
          370
        ],
        [
          440,
          358
        ],
        [
          462,
          340
        ],
        [
          478,
          318
        ],
        [
          493,
          303
        ],
        [
          434,
          322
        ],
        [
          0,
          0
        ],
        [
          0,
          0
        ],
        [
          0,
          0
        ],
        [
          418,
          324
        ],
        [
          419,
          286
        ],
        [
          417,
          281
        ],
        [
          415,
          267
        ],
        [
          402,
          337
        ],
        [
          392,
          306
        ],
        [
          390,
          296
        ],
        [
          388,
          288
        ],
        [
          392,
          355
        ],
        [
          373,
          339
        ],
        [
          369,
          335
        ],
        [
          367,
          331
        ]
      ]
    ],
    "frame_index": 3
  },
  {
    "hands": [
      [
        [
          411,
          376
        ],
        [
          398,
          380
        ],
        [
          385,
          376
        ],
        [
          364,
          364
        ],
        [
          353,
          360
        ],
        [
          414,
          339
        ],
        [
          413,
          312
        ],
        [
          412,
          313
        ],
        [
          415,
          309
        ],
        [
          428,
          343
        ],
        [
          445,
          314
        ],
        [
          448,
          303
        ],
        [
          448,
          293
        ],
        [
          439,
          350
        ],
        [
          443,
          313
        ],
        [
          448,
          305
        ],
        [
          449,
          301
        ],
        [
          451,
          357
        ],
        [
          470,
          340
        ],
        [
          477,
          334
        ],
        [
          0,
          0
        ]
      ]
    ],
    "frame_index": 4
  },
  {
    "hands": [
      [
        [
          418,
          387
        ],
        [
          429,
          374
        ],
        [
          431,
          354
        ],
        [
          437,
          332
        ],
        [
          439,
          314
        ],
        [
          406,
          360
        ],
        [
          395,
          343
        ],
        [
          389,
          334
        ],
        [
          382,
          328
        ],
        [
          394,
          369
        ],
        [
          388,
          343
        ],
        [
          387,
          337
        ],
        [
          382,
          328
        ],
        [
          384,
          375
        ],
        [
          367,
          361
        ],
        [
          355,
          352
        ],
        [
          348,
          347
        ],
        [
          376,
          386
        ],
        [
          352,
          378
        ],
        [
          341,
          375
        ],
        [
          331,
          370
        ]
      ]
    ],
    "frame_index": 5
  },
  {
    "hands": [
      [
        [
          416,
          383
        ],
        [
          431,
          379
        ],
        [
          445,
          381
        ],
        [
          431,
          325
        ],
        [
          431,
          304
        ],
        [
          398,
          355
        ],
        [
          387,
          334
        ],
        [
          377,
          322
        ],
        [
          371,
          309
        ],
        [
          385,
          361
        ],
        [
          363,
          344
        ],
        [
          351,
          332
        ],
        [
          341,
          323
        ],
        [
          377,
          367
        ],
        [
          356,
          348
        ],
        [
          343,
          337
        ],
        [
          334,
          330
        ],
        [
          371,
          374
        ],
        [
          350,
          364
        ],
        [
          335,
          358
        ],
        [
          324,
          350
        ]
      ]
    ],
    "frame_index": 6
  },
  {
    "hands": [
      [
        [
          417,
          373
        ],
        [
          433,
          371
        ],
        [
          448,
          368
        ],
        [
          470,
          368
        ],
        [
          494,
          365
        ],
        [
          421,
          339
        ],
        [
          429,
          316
        ],
        [
          433,
          298
        ],
        [
          434,
          281
        ],
        [
          400,
          337
        ],
        [
          394,
          309
        ],
        [
          387,
          292
        ],
        [
          385,
          275
        ],
        [
          385,
          344
        ],
        [
          367,
          315
        ],
        [
          359,
          300
        ],
        [
          358,
          286
        ],
        [
          370,
          352
        ],
        [
          351,
          334
        ],
        [
          339,
          324
        ],
        [
          331,
          314
        ]
      ]
    ],
    "frame_index": 7
  },
  {
    "hands": [
      [
        [
          417,
          373
        ],
        [
          433,
          371
        ],
        [
          448,
          368
        ],
        [
          470,
          368
        ],
        [
          494,
          365
        ],
        [
          421,
          339
        ],
        [
          429,
          316
        ],
        [
          433,
          298
        ],
        [
          434,
          281
        ],
        [
          400,
          337
        ],
        [
          394,
          309
        ],
        [
          387,
          292
        ],
        [
          385,
          275
        ],
        [
          385,
          344
        ],
        [
          367,
          315
        ],
        [
          359,
          301
        ],
        [
          358,
          286
        ],
        [
          370,
          352
        ],
        [
          351,
          334
        ],
        [
          339,
          324
        ],
        [
          331,
          314
        ]
      ]
    ],
    "frame_index": 8
  },
  {
    "hands": [
      [
        [
          424,
          361
        ],
        [
          440,
          356
        ],
        [
          452,
          352
        ],
        [
          476,
          349
        ],
        [
          500,
          347
        ],
        [
          430,
          319
        ],
        [
          437,
          293
        ],
        [
          442,
          273
        ],
        [
          445,
          254
        ],
        [
          409,
          316
        ],
        [
          404,
          286
        ],
        [
          397,
          265
        ],
        [
          396,
          247
        ],
        [
          392,
          322
        ],
        [
          378,
          290
        ],
        [
          371,
          274
        ],
        [
          368,
          258
        ],
        [
          377,
          331
        ],
        [
          362,
          310
        ],
        [
          352,
          298
        ],
        [
          344,
          284
        ]
      ]
    ],
    "frame_index": 9
  },
  {
    "hands": [
      [
        [
          428,
          347
        ],
        [
          445,
          341
        ],
        [
          460,
          337
        ],
        [
          485,
          334
        ],
        [
          506,
          333
        ],
        [
          440,
          299
        ],
        [
          447,
          271
        ],
        [
          454,
          250
        ],
        [
          458,
          231
        ],
        [
          420,
          294
        ],
        [
          418,
          264
        ],
        [
          412,
          242
        ],
        [
          413,
          223
        ],
        [
          402,
          299
        ],
        [
          393,
          268
        ],
        [
          386,
          248
        ],
        [
          387,
          231
        ],
        [
          386,
          307
        ],
        [
          373,
          285
        ],
        [
          365,
          272
        ],
        [
          358,
          259
        ]
      ]
    ],
    "frame_index": 10
  },
  {
    "hands": [
      [
        [
          434,
          332
        ],
        [
          453,
          326
        ],
        [
          469,
          323
        ],
        [
          492,
          320
        ],
        [
          513,
          321
        ],
        [
          450,
          282
        ],
        [
          460,
          252
        ],
        [
          466,
          233
        ],
        [
          470,
          214
        ],
        [
          430,
          278
        ],
        [
          430,
          244
        ],
        [
          428,
          222
        ],
        [
          429,
          203
        ],
        [
          413,
          282
        ],
        [
          408,
          249
        ],
        [
          403,
          229
        ],
        [
          403,
          210
        ],
        [
          395,
          289
        ],
        [
          387,
          264
        ],
        [
          380,
          250
        ],
        [
          375,
          235
        ]
      ]
    ],
    "frame_index": 11
  },
  {
    "hands": [
      [
        [
          437,
          325
        ],
        [
          457,
          317
        ],
        [
          476,
          312
        ],
        [
          496,
          308
        ],
        [
          516,
          309
        ],
        [
          456,
          271
        ],
        [
          465,
          240
        ],
        [
          471,
          221
        ],
        [
          474,
          203
        ],
        [
          436,
          267
        ],
        [
          437,
          231
        ],
        [
          436,
          211
        ],
        [
          436,
          192
        ],
        [
          420,
          270
        ],
        [
          416,
          236
        ],
        [
          413,
          216
        ],
        [
          413,
          198
        ],
        [
          403,
          275
        ],
        [
          396,
          251
        ],
        [
          390,
          237
        ],
        [
          384,
          222
        ]
      ]
    ],
    "frame_index": 12
  },
  {
    "hands": [
      [
        [
          438,
          320
        ],
        [
          460,
          310
        ],
        [
          479,
          304
        ],
        [
          499,
          300
        ],
        [
          519,
          300
        ],
        [
          461,
          262
        ],
        [
          469,
          231
        ],
        [
          474,
          213
        ],
        [
          477,
          196
        ],
        [
          441,
          258
        ],
        [
          442,
          224
        ],
        [
          443,
          205
        ],
        [
          444,
          187
        ],
        [
          425,
          261
        ],
        [
          423,
          228
        ],
        [
          421,
          209
        ],
        [
          422,
          192
        ],
        [
          408,
          266
        ],
        [
          402,
          242
        ],
        [
          398,
          227
        ],
        [
          394,
          211
        ]
      ]
    ],
    "frame_index": 13
  },
  {
    "hands": [
      [
        [
          438,
          320
        ],
        [
          459,
          310
        ],
        [
          479,
          304
        ],
        [
          499,
          300
        ],
        [
          519,
          300
        ],
        [
          461,
          263
        ],
        [
          469,
          231
        ],
        [
          473,
          213
        ],
        [
          477,
          196
        ],
        [
          441,
          258
        ],
        [
          443,
          224
        ],
        [
          443,
          205
        ],
        [
          444,
          187
        ],
        [
          425,
          261
        ],
        [
          423,
          228
        ],
        [
          421,
          209
        ],
        [
          422,
          192
        ],
        [
          407,
          266
        ],
        [
          402,
          242
        ],
        [
          397,
          227
        ],
        [
          394,
          211
        ]
      ]
    ],
    "frame_index": 14
  },
  {
    "hands": [
      [
        [
          439,
          317
        ],
        [
          461,
          305
        ],
        [
          484,
          299
        ],
        [
          501,
          295
        ],
        [
          519,
          295
        ],
        [
          464,
          257
        ],
        [
          472,
          226
        ],
        [
          476,
          209
        ],
        [
          479,
          194
        ],
        [
          445,
          254
        ],
        [
          447,
          219
        ],
        [
          448,
          201
        ],
        [
          450,
          189
        ],
        [
          429,
          256
        ],
        [
          429,
          223
        ],
        [
          428,
          205
        ],
        [
          430,
          190
        ],
        [
          411,
          260
        ],
        [
          408,
          235
        ],
        [
          405,
          220
        ],
        [
          403,
          205
        ]
      ]
    ],
    "frame_index": 15
  },
  {
    "hands": [
      [
        [
          438,
          316
        ],
        [
          462,
          303
        ],
        [
          484,
          297
        ],
        [
          501,
          293
        ],
        [
          519,
          292
        ],
        [
          464,
          255
        ],
        [
          473,
          224
        ],
        [
          476,
          208
        ],
        [
          479,
          194
        ],
        [
          446,
          251
        ],
        [
          448,
          217
        ],
        [
          451,
          201
        ],
        [
          455,
          191
        ],
        [
          431,
          253
        ],
        [
          432,
          221
        ],
        [
          434,
          204
        ],
        [
          435,
          190
        ],
        [
          414,
          256
        ],
        [
          413,
          232
        ],
        [
          412,
          218
        ],
        [
          412,
          205
        ]
      ]
    ],
    "frame_index": 16
  },
  {
    "hands": [
      [
        [
          439,
          313
        ],
        [
          463,
          302
        ],
        [
          486,
          296
        ],
        [
          501,
          294
        ],
        [
          518,
          291
        ],
        [
          466,
          253
        ],
        [
          473,
          223
        ],
        [
          476,
          208
        ],
        [
          478,
          197
        ],
        [
          447,
          250
        ],
        [
          451,
          217
        ],
        [
          453,
          201
        ],
        [
          456,
          196
        ],
        [
          432,
          251
        ],
        [
          434,
          220
        ],
        [
          437,
          204
        ],
        [
          438,
          192
        ],
        [
          416,
          253
        ],
        [
          416,
          230
        ],
        [
          416,
          217
        ],
        [
          419,
          205
        ]
      ]
    ],
    "frame_index": 17
  },
  {
    "hands": [
      [
        [
          439,
          313
        ],
        [
          463,
          301
        ],
        [
          485,
          296
        ],
        [
          500,
          294
        ],
        [
          516,
          290
        ],
        [
          467,
          253
        ],
        [
          473,
          222
        ],
        [
          475,
          208
        ],
        [
          476,
          201
        ],
        [
          449,
          248
        ],
        [
          453,
          215
        ],
        [
          456,
          202
        ],
        [
          460,
          198
        ],
        [
          434,
          249
        ],
        [
          437,
          220
        ],
        [
          440,
          206
        ],
        [
          443,
          196
        ],
        [
          418,
          253
        ],
        [
          420,
          230
        ],
        [
          421,
          218
        ],
        [
          425,
          207
        ]
      ]
    ],
    "frame_index": 18
  },
  {
    "hands": [
      [
        [
          438,
          314
        ],
        [
          463,
          302
        ],
        [
          485,
          298
        ],
        [
          500,
          297
        ],
        [
          515,
          291
        ],
        [
          468,
          254
        ],
        [
          473,
          222
        ],
        [
          474,
          210
        ],
        [
          475,
          206
        ],
        [
          450,
          250
        ],
        [
          454,
          216
        ],
        [
          458,
          202
        ],
        [
          464,
          208
        ],
        [
          435,
          250
        ],
        [
          439,
          221
        ],
        [
          442,
          207
        ],
        [
          445,
          200
        ],
        [
          419,
          254
        ],
        [
          423,
          230
        ],
        [
          424,
          217
        ],
        [
          429,
          210
        ]
      ]
    ],
    "frame_index": 19
  },
  {
    "hands": [
      [
        [
          438,
          314
        ],
        [
          463,
          302
        ],
        [
          486,
          297
        ],
        [
          501,
          297
        ],
        [
          514,
          290
        ],
        [
          468,
          254
        ],
        [
          473,
          222
        ],
        [
          474,
          210
        ],
        [
          475,
          205
        ],
        [
          450,
          250
        ],
        [
          454,
          216
        ],
        [
          458,
          202
        ],
        [
          464,
          207
        ],
        [
          435,
          251
        ],
        [
          438,
          220
        ],
        [
          442,
          207
        ],
        [
          445,
          201
        ],
        [
          419,
          254
        ],
        [
          423,
          230
        ],
        [
          424,
          218
        ],
        [
          429,
          211
        ]
      ]
    ],
    "frame_index": 20
  },
  {
    "hands": [
      [
        [
          438,
          315
        ],
        [
          464,
          303
        ],
        [
          489,
          299
        ],
        [
          501,
          298
        ],
        [
          511,
          290
        ],
        [
          469,
          256
        ],
        [
          472,
          223
        ],
        [
          475,
          213
        ],
        [
          475,
          209
        ],
        [
          450,
          252
        ],
        [
          456,
          221
        ],
        [
          459,
          205
        ],
        [
          462,
          213
        ],
        [
          436,
          252
        ],
        [
          440,
          222
        ],
        [
          443,
          208
        ],
        [
          445,
          205
        ],
        [
          420,
          254
        ],
        [
          425,
          230
        ],
        [
          427,
          218
        ],
        [
          431,
          216
        ]
      ]
    ],
    "frame_index": 21
  },
  {
    "hands": [
      [
        [
          438,
          316
        ],
        [
          466,
          305
        ],
        [
          491,
          300
        ],
        [
          501,
          300
        ],
        [
          508,
          291
        ],
        [
          469,
          257
        ],
        [
          473,
          224
        ],
        [
          475,
          214
        ],
        [
          475,
          212
        ],
        [
          451,
          255
        ],
        [
          456,
          221
        ],
        [
          460,
          207
        ],
        [
          463,
          217
        ],
        [
          436,
          254
        ],
        [
          441,
          223
        ],
        [
          443,
          210
        ],
        [
          445,
          210
        ],
        [
          420,
          255
        ],
        [
          426,
          229
        ],
        [
          428,
          222
        ],
        [
          432,
          222
        ]
      ]
    ],
    "frame_index": 22
  },
  {
    "hands": [
      [
        [
          437,
          317
        ],
        [
          465,
          305
        ],
        [
          493,
          301
        ],
        [
          500,
          299
        ],
        [
          503,
          290
        ],
        [
          470,
          257
        ],
        [
          473,
          221
        ],
        [
          475,
          216
        ],
        [
          474,
          221
        ],
        [
          451,
          252
        ],
        [
          458,
          213
        ],
        [
          460,
          210
        ],
        [
          462,
          221
        ],
        [
          436,
          252
        ],
        [
          443,
          217
        ],
        [
          443,
          213
        ],
        [
          446,
          218
        ],
        [
          420,
          256
        ],
        [
          426,
          228
        ],
        [
          428,
          225
        ],
        [
          432,
          229
        ]
      ]
    ],
    "frame_index": 23
  },
  {
    "hands": [
      [
        [
          437,
          316
        ],
        [
          464,
          306
        ],
        [
          491,
          301
        ],
        [
          500,
          300
        ],
        [
          498,
          288
        ],
        [
          470,
          256
        ],
        [
          474,
          221
        ],
        [
          473,
          220
        ],
        [
          469,
          228
        ],
        [
          451,
          251
        ],
        [
          458,
          213
        ],
        [
          460,
          214
        ],
        [
          461,
          225
        ],
        [
          436,
          251
        ],
        [
          442,
          219
        ],
        [
          442,
          216
        ],
        [
          445,
          224
        ],
        [
          420,
          256
        ],
        [
          425,
          229
        ],
        [
          429,
          227
        ],
        [
          432,
          236
        ]
      ]
    ],
    "frame_index": 24
  },
  {
    "hands": [
      [
        [
          437,
          317
        ],
        [
          465,
          306
        ],
        [
          489,
          300
        ],
        [
          500,
          300
        ],
        [
          494,
          288
        ],
        [
          470,
          257
        ],
        [
          475,
          223
        ],
        [
          475,
          224
        ],
        [
          474,
          232
        ],
        [
          451,
          251
        ],
        [
          458,
          216
        ],
        [
          460,
          216
        ],
        [
          461,
          227
        ],
        [
          436,
          250
        ],
        [
          442,
          219
        ],
        [
          442,
          217
        ],
        [
          446,
          226
        ],
        [
          419,
          256
        ],
        [
          426,
          230
        ],
        [
          429,
          230
        ],
        [
          431,
          240
        ]
      ]
    ],
    "frame_index": 25
  },
  {
    "hands": [
      [
        [
          437,
          317
        ],
        [
          465,
          306
        ],
        [
          489,
          300
        ],
        [
          499,
          300
        ],
        [
          494,
          287
        ],
        [
          471,
          257
        ],
        [
          475,
          223
        ],
        [
          475,
          224
        ],
        [
          474,
          232
        ],
        [
          451,
          251
        ],
        [
          458,
          216
        ],
        [
          460,
          216
        ],
        [
          460,
          227
        ],
        [
          436,
          250
        ],
        [
          442,
          218
        ],
        [
          442,
          217
        ],
        [
          445,
          228
        ],
        [
          419,
          256
        ],
        [
          426,
          230
        ],
        [
          429,
          230
        ],
        [
          431,
          240
        ]
      ]
    ],
    "frame_index": 26
  },
  {
    "hands": [
      [
        [
          436,
          319
        ],
        [
          466,
          307
        ],
        [
          494,
          301
        ],
        [
          495,
          297
        ],
        [
          487,
          289
        ],
        [
          470,
          257
        ],
        [
          475,
          226
        ],
        [
          475,
          229
        ],
        [
          473,
          238
        ],
        [
          451,
          251
        ],
        [
          459,
          217
        ],
        [
          460,
          219
        ],
        [
          461,
          230
        ],
        [
          435,
          252
        ],
        [
          441,
          219
        ],
        [
          442,
          220
        ],
        [
          446,
          231
        ],
        [
          419,
          257
        ],
        [
          425,
          232
        ],
        [
          428,
          233
        ],
        [
          429,
          245
        ]
      ]
    ],
    "frame_index": 27
  },
  {
    "hands": [
      [
        [
          437,
          318
        ],
        [
          466,
          308
        ],
        [
          493,
          301
        ],
        [
          492,
          297
        ],
        [
          485,
          290
        ],
        [
          470,
          257
        ],
        [
          474,
          227
        ],
        [
          474,
          232
        ],
        [
          473,
          241
        ],
        [
          452,
          249
        ],
        [
          458,
          219
        ],
        [
          459,
          222
        ],
        [
          459,
          234
        ],
        [
          435,
          249
        ],
        [
          440,
          222
        ],
        [
          441,
          224
        ],
        [
          444,
          235
        ],
        [
          418,
          257
        ],
        [
          423,
          234
        ],
        [
          426,
          237
        ],
        [
          428,
          249
        ]
      ]
    ],
    "frame_index": 28
  },
  {
    "hands": [
      [
        [
          438,
          319
        ],
        [
          465,
          309
        ],
        [
          492,
          302
        ],
        [
          491,
          298
        ],
        [
          481,
          291
        ],
        [
          471,
          256
        ],
        [
          474,
          229
        ],
        [
          473,
          235
        ],
        [
          472,
          244
        ],
        [
          452,
          249
        ],
        [
          457,
          222
        ],
        [
          459,
          226
        ],
        [
          460,
          237
        ],
        [
          434,
          250
        ],
        [
          439,
          224
        ],
        [
          440,
          228
        ],
        [
          443,
          239
        ],
        [
          418,
          257
        ],
        [
          421,
          237
        ],
        [
          425,
          241
        ],
        [
          427,
          252
        ]
      ]
    ],
    "frame_index": 29
  },
  {
    "hands": [
      [
        [
          438,
          321
        ],
        [
          465,
          312
        ],
        [
          491,
          304
        ],
        [
          490,
          299
        ],
        [
          478,
          295
        ],
        [
          471,
          257
        ],
        [
          474,
          232
        ],
        [
          472,
          237
        ],
        [
          472,
          246
        ],
        [
          452,
          250
        ],
        [
          455,
          223
        ],
        [
          458,
          230
        ],
        [
          459,
          243
        ],
        [
          434,
          252
        ],
        [
          438,
          227
        ],
        [
          439,
          230
        ],
        [
          441,
          244
        ],
        [
          417,
          260
        ],
        [
          420,
          240
        ],
        [
          424,
          245
        ],
        [
          426,
          256
        ]
      ]
    ],
    "frame_index": 30
  },
  {
    "hands": [
      [
        [
          438,
          322
        ],
        [
          463,
          313
        ],
        [
          491,
          303
        ],
        [
          487,
          300
        ],
        [
          478,
          299
        ],
        [
          470,
          261
        ],
        [
          473,
          234
        ],
        [
          471,
          236
        ],
        [
          467,
          250
        ],
        [
          450,
          253
        ],
        [
          455,
          227
        ],
        [
          456,
          234
        ],
        [
          457,
          248
        ],
        [
          433,
          255
        ],
        [
          437,
          229
        ],
        [
          438,
          235
        ],
        [
          440,
          247
        ],
        [
          416,
          262
        ],
        [
          419,
          243
        ],
        [
          422,
          247
        ],
        [
          424,
          258
        ]
      ]
    ],
    "frame_index": 31
  },
  {
    "hands": [
      [
        [
          437,
          323
        ],
        [
          464,
          313
        ],
        [
          491,
          303
        ],
        [
          488,
          300
        ],
        [
          479,
          299
        ],
        [
          470,
          261
        ],
        [
          473,
          234
        ],
        [
          471,
          236
        ],
        [
          469,
          251
        ],
        [
          451,
          252
        ],
        [
          455,
          227
        ],
        [
          456,
          234
        ],
        [
          457,
          247
        ],
        [
          433,
          255
        ],
        [
          437,
          229
        ],
        [
          438,
          235
        ],
        [
          440,
          247
        ],
        [
          416,
          263
        ],
        [
          420,
          243
        ],
        [
          422,
          247
        ],
        [
          424,
          259
        ]
      ]
    ],
    "frame_index": 32
  },
  {
    "hands": [
      [
        [
          437,
          325
        ],
        [
          464,
          316
        ],
        [
          491,
          304
        ],
        [
          488,
          302
        ],
        [
          477,
          302
        ],
        [
          468,
          264
        ],
        [
          471,
          237
        ],
        [
          470,
          244
        ],
        [
          468,
          257
        ],
        [
          449,
          258
        ],
        [
          453,
          230
        ],
        [
          455,
          238
        ],
        [
          456,
          252
        ],
        [
          432,
          259
        ],
        [
          436,
          232
        ],
        [
          438,
          237
        ],
        [
          439,
          252
        ],
        [
          415,
          267
        ],
        [
          419,
          246
        ],
        [
          422,
          251
        ],
        [
          424,
          263
        ]
      ]
    ],
    "frame_index": 33
  },
  {
    "hands": [
      [
        [
          438,
          326
        ],
        [
          465,
          318
        ],
        [
          491,
          307
        ],
        [
          487,
          305
        ],
        [
          477,
          306
        ],
        [
          467,
          265
        ],
        [
          470,
          241
        ],
        [
          469,
          248
        ],
        [
          467,
          262
        ],
        [
          449,
          260
        ],
        [
          452,
          233
        ],
        [
          454,
          242
        ],
        [
          454,
          256
        ],
        [
          432,
          263
        ],
        [
          435,
          236
        ],
        [
          436,
          241
        ],
        [
          438,
          257
        ],
        [
          414,
          271
        ],
        [
          418,
          249
        ],
        [
          421,
          255
        ],
        [
          423,
          266
        ]
      ]
    ],
    "frame_index": 34
  },
  {
    "hands": [
      [
        [
          437,
          331
        ],
        [
          465,
          321
        ],
        [
          491,
          309
        ],
        [
          488,
          307
        ],
        [
          475,
          308
        ],
        [
          467,
          270
        ],
        [
          470,
          243
        ],
        [
          469,
          252
        ],
        [
          468,
          266
        ],
        [
          449,
          266
        ],
        [
          452,
          236
        ],
        [
          455,
          246
        ],
        [
          454,
          260
        ],
        [
          432,
          267
        ],
        [
          435,
          240
        ],
        [
          437,
          244
        ],
        [
          438,
          261
        ],
        [
          415,
          274
        ],
        [
          418,
          252
        ],
        [
          422,
          258
        ],
        [
          423,
          269
        ]
      ]
    ],
    "frame_index": 35
  },
  {
    "hands": [
      [
        [
          437,
          335
        ],
        [
          465,
          326
        ],
        [
          492,
          312
        ],
        [
          489,
          310
        ],
        [
          477,
          311
        ],
        [
          469,
          273
        ],
        [
          471,
          247
        ],
        [
          472,
          257
        ],
        [
          469,
          271
        ],
        [
          449,
          270
        ],
        [
          454,
          239
        ],
        [
          456,
          250
        ],
        [
          456,
          264
        ],
        [
          434,
          271
        ],
        [
          436,
          243
        ],
        [
          438,
          249
        ],
        [
          440,
          265
        ],
        [
          416,
          277
        ],
        [
          420,
          255
        ],
        [
          423,
          261
        ],
        [
          424,
          272
        ]
      ]
    ],
    "frame_index": 36
  },
  {
    "hands": [
      [
        [
          439,
          338
        ],
        [
          467,
          329
        ],
        [
          493,
          315
        ],
        [
          491,
          313
        ],
        [
          479,
          316
        ],
        [
          470,
          278
        ],
        [
          473,
          251
        ],
        [
          473,
          260
        ],
        [
          472,
          273
        ],
        [
          452,
          275
        ],
        [
          455,
          243
        ],
        [
          459,
          254
        ],
        [
          458,
          269
        ],
        [
          435,
          275
        ],
        [
          438,
          247
        ],
        [
          440,
          252
        ],
        [
          442,
          269
        ],
        [
          418,
          281
        ],
        [
          422,
          258
        ],
        [
          425,
          265
        ],
        [
          427,
          276
        ]
      ]
    ],
    "frame_index": 37
  },
  {
    "hands": [
      [
        [
          439,
          338
        ],
        [
          467,
          329
        ],
        [
          493,
          315
        ],
        [
          491,
          313
        ],
        [
          479,
          316
        ],
        [
          470,
          278
        ],
        [
          473,
          251
        ],
        [
          473,
          260
        ],
        [
          472,
          274
        ],
        [
          452,
          275
        ],
        [
          455,
          243
        ],
        [
          459,
          254
        ],
        [
          458,
          269
        ],
        [
          435,
          275
        ],
        [
          438,
          247
        ],
        [
          440,
          252
        ],
        [
          442,
          269
        ],
        [
          418,
          281
        ],
        [
          422,
          258
        ],
        [
          425,
          265
        ],
        [
          427,
          276
        ]
      ]
    ],
    "frame_index": 38
  },
  {
    "hands": [
      [
        [
          439,
          341
        ],
        [
          467,
          332
        ],
        [
          494,
          321
        ],
        [
          493,
          316
        ],
        [
          479,
          318
        ],
        [
          472,
          282
        ],
        [
          475,
          254
        ],
        [
          476,
          264
        ],
        [
          474,
          278
        ],
        [
          453,
          277
        ],
        [
          457,
          246
        ],
        [
          460,
          258
        ],
        [
          459,
          271
        ],
        [
          437,
          278
        ],
        [
          440,
          250
        ],
        [
          442,
          256
        ],
        [
          444,
          274
        ],
        [
          419,
          284
        ],
        [
          424,
          261
        ],
        [
          427,
          268
        ],
        [
          428,
          280
        ]
      ]
    ],
    "frame_index": 39
  },
  {
    "hands": [
      [
        [
          440,
          343
        ],
        [
          468,
          334
        ],
        [
          495,
          321
        ],
        [
          493,
          318
        ],
        [
          481,
          320
        ],
        [
          473,
          283
        ],
        [
          476,
          256
        ],
        [
          477,
          267
        ],
        [
          474,
          281
        ],
        [
          453,
          280
        ],
        [
          458,
          248
        ],
        [
          461,
          260
        ],
        [
          461,
          274
        ],
        [
          438,
          280
        ],
        [
          441,
          252
        ],
        [
          444,
          259
        ],
        [
          445,
          275
        ],
        [
          420,
          286
        ],
        [
          425,
          264
        ],
        [
          428,
          270
        ],
        [
          429,
          282
        ]
      ]
    ],
    "frame_index": 40
  },
  {
    "hands": [
      [
        [
          441,
          344
        ],
        [
          469,
          335
        ],
        [
          496,
          322
        ],
        [
          493,
          319
        ],
        [
          481,
          322
        ],
        [
          474,
          284
        ],
        [
          476,
          257
        ],
        [
          477,
          268
        ],
        [
          475,
          282
        ],
        [
          454,
          281
        ],
        [
          459,
          249
        ],
        [
          462,
          261
        ],
        [
          461,
          276
        ],
        [
          438,
          282
        ],
        [
          441,
          253
        ],
        [
          444,
          260
        ],
        [
          445,
          277
        ],
        [
          420,
          288
        ],
        [
          425,
          265
        ],
        [
          428,
          271
        ],
        [
          429,
          283
        ]
      ]
    ],
    "frame_index": 41
  },
  {
    "hands": [
      [
        [
          442,
          342
        ],
        [
          468,
          336
        ],
        [
          494,
          327
        ],
        [
          494,
          319
        ],
        [
          481,
          322
        ],
        [
          474,
          285
        ],
        [
          476,
          258
        ],
        [
          477,
          268
        ],
        [
          475,
          281
        ],
        [
          454,
          283
        ],
        [
          459,
          249
        ],
        [
          462,
          261
        ],
        [
          462,
          276
        ],
        [
          439,
          282
        ],
        [
          442,
          253
        ],
        [
          444,
          261
        ],
        [
          446,
          277
        ],
        [
          421,
          287
        ],
        [
          426,
          265
        ],
        [
          429,
          271
        ],
        [
          430,
          283
        ]
      ]
    ],
    "frame_index": 42
  },
  {
    "hands": [
      [
        [
          442,
          343
        ],
        [
          469,
          335
        ],
        [
          496,
          322
        ],
        [
          494,
          319
        ],
        [
          482,
          321
        ],
        [
          474,
          284
        ],
        [
          477,
          257
        ],
        [
          478,
          267
        ],
        [
          476,
          281
        ],
        [
          454,
          283
        ],
        [
          459,
          249
        ],
        [
          462,
          261
        ],
        [
          462,
          277
        ],
        [
          440,
          281
        ],
        [
          442,
          252
        ],
        [
          445,
          260
        ],
        [
          446,
          277
        ],
        [
          422,
          285
        ],
        [
          426,
          265
        ],
        [
          429,
          270
        ],
        [
          430,
          282
        ]
      ]
    ],
    "frame_index": 43
  },
  {
    "hands": [
      [
        [
          442,
          343
        ],
        [
          469,
          335
        ],
        [
          496,
          323
        ],
        [
          494,
          319
        ],
        [
          481,
          321
        ],
        [
          474,
          285
        ],
        [
          477,
          257
        ],
        [
          478,
          267
        ],
        [
          476,
          281
        ],
        [
          454,
          284
        ],
        [
          459,
          249
        ],
        [
          462,
          261
        ],
        [
          462,
          277
        ],
        [
          440,
          281
        ],
        [
          443,
          253
        ],
        [
          445,
          259
        ],
        [
          447,
          277
        ],
        [
          422,
          286
        ],
        [
          426,
          264
        ],
        [
          429,
          270
        ],
        [
          431,
          283
        ]
      ]
    ],
    "frame_index": 44
  },
  {
    "hands": [
      [
        [
          442,
          343
        ],
        [
          469,
          335
        ],
        [
          496,
          321
        ],
        [
          495,
          318
        ],
        [
          482,
          321
        ],
        [
          475,
          283
        ],
        [
          477,
          256
        ],
        [
          478,
          266
        ],
        [
          476,
          280
        ],
        [
          455,
          280
        ],
        [
          460,
          248
        ],
        [
          463,
          260
        ],
        [
          463,
          275
        ],
        [
          440,
          281
        ],
        [
          443,
          252
        ],
        [
          445,
          259
        ],
        [
          447,
          276
        ],
        [
          422,
          286
        ],
        [
          427,
          264
        ],
        [
          429,
          270
        ],
        [
          431,
          282
        ]
      ]
    ],
    "frame_index": 45
  },
  {
    "hands": [
      [
        [
          442,
          342
        ],
        [
          470,
          334
        ],
        [
          497,
          321
        ],
        [
          495,
          318
        ],
        [
          482,
          320
        ],
        [
          475,
          283
        ],
        [
          478,
          256
        ],
        [
          479,
          266
        ],
        [
          477,
          280
        ],
        [
          455,
          282
        ],
        [
          460,
          248
        ],
        [
          463,
          259
        ],
        [
          463,
          275
        ],
        [
          440,
          280
        ],
        [
          443,
          252
        ],
        [
          445,
          259
        ],
        [
          447,
          275
        ],
        [
          422,
          286
        ],
        [
          427,
          264
        ],
        [
          430,
          269
        ],
        [
          431,
          282
        ]
      ]
    ],
    "frame_index": 46
  },
  {
    "hands": [
      [
        [
          442,
          341
        ],
        [
          469,
          334
        ],
        [
          497,
          321
        ],
        [
          496,
          316
        ],
        [
          482,
          320
        ],
        [
          474,
          283
        ],
        [
          478,
          255
        ],
        [
          478,
          265
        ],
        [
          477,
          278
        ],
        [
          456,
          279
        ],
        [
          460,
          248
        ],
        [
          463,
          259
        ],
        [
          463,
          274
        ],
        [
          441,
          280
        ],
        [
          443,
          251
        ],
        [
          445,
          258
        ],
        [
          447,
          275
        ],
        [
          423,
          285
        ],
        [
          427,
          263
        ],
        [
          430,
          269
        ],
        [
          431,
          281
        ]
      ]
    ],
    "frame_index": 47
  },
  {
    "hands": [
      [
        [
          441,
          342
        ],
        [
          469,
          334
        ],
        [
          495,
          325
        ],
        [
          495,
          317
        ],
        [
          482,
          319
        ],
        [
          475,
          282
        ],
        [
          477,
          255
        ],
        [
          478,
          265
        ],
        [
          476,
          279
        ],
        [
          455,
          280
        ],
        [
          460,
          247
        ],
        [
          463,
          258
        ],
        [
          463,
          274
        ],
        [
          440,
          279
        ],
        [
          443,
          251
        ],
        [
          445,
          257
        ],
        [
          447,
          274
        ],
        [
          423,
          284
        ],
        [
          427,
          263
        ],
        [
          430,
          268
        ],
        [
          431,
          280
        ]
      ]
    ],
    "frame_index": 48
  },
  {
    "hands": [
      [
        [
          441,
          341
        ],
        [
          469,
          333
        ],
        [
          496,
          321
        ],
        [
          495,
          316
        ],
        [
          483,
          319
        ],
        [
          475,
          282
        ],
        [
          477,
          255
        ],
        [
          478,
          264
        ],
        [
          476,
          278
        ],
        [
          456,
          278
        ],
        [
          460,
          247
        ],
        [
          463,
          258
        ],
        [
          463,
          273
        ],
        [
          440,
          279
        ],
        [
          443,
          250
        ],
        [
          445,
          257
        ],
        [
          447,
          274
        ],
        [
          423,
          285
        ],
        [
          427,
          263
        ],
        [
          430,
          267
        ],
        [
          431,
          280
        ]
      ]
    ],
    "frame_index": 49
  },
  {
    "hands": [
      [
        [
          441,
          342
        ],
        [
          469,
          333
        ],
        [
          496,
          324
        ],
        [
          496,
          316
        ],
        [
          482,
          318
        ],
        [
          475,
          281
        ],
        [
          477,
          255
        ],
        [
          479,
          264
        ],
        [
          476,
          278
        ],
        [
          456,
          279
        ],
        [
          460,
          247
        ],
        [
          463,
          258
        ],
        [
          462,
          273
        ],
        [
          440,
          279
        ],
        [
          442,
          250
        ],
        [
          445,
          257
        ],
        [
          446,
          274
        ],
        [
          423,
          285
        ],
        [
          427,
          263
        ],
        [
          430,
          267
        ],
        [
          431,
          280
        ]
      ]
    ],
    "frame_index": 50
  },
  {
    "hands": [
      [
        [
          442,
          342
        ],
        [
          470,
          333
        ],
        [
          495,
          325
        ],
        [
          496,
          316
        ],
        [
          482,
          318
        ],
        [
          475,
          281
        ],
        [
          478,
          254
        ],
        [
          478,
          264
        ],
        [
          477,
          278
        ],
        [
          457,
          279
        ],
        [
          460,
          247
        ],
        [
          463,
          257
        ],
        [
          462,
          272
        ],
        [
          440,
          280
        ],
        [
          443,
          251
        ],
        [
          445,
          256
        ],
        [
          447,
          273
        ],
        [
          423,
          285
        ],
        [
          427,
          262
        ],
        [
          430,
          268
        ],
        [
          431,
          280
        ]
      ]
    ],
    "frame_index": 51
  },
  {
    "hands": [
      [
        [
          442,
          343
        ],
        [
          470,
          333
        ],
        [
          496,
          326
        ],
        [
          497,
          316
        ],
        [
          483,
          318
        ],
        [
          475,
          282
        ],
        [
          478,
          254
        ],
        [
          479,
          264
        ],
        [
          477,
          277
        ],
        [
          457,
          279
        ],
        [
          460,
          247
        ],
        [
          464,
          257
        ],
        [
          463,
          272
        ],
        [
          440,
          279
        ],
        [
          443,
          251
        ],
        [
          445,
          256
        ],
        [
          447,
          273
        ],
        [
          423,
          285
        ],
        [
          427,
          262
        ],
        [
          430,
          268
        ],
        [
          432,
          280
        ]
      ]
    ],
    "frame_index": 52
  },
  {
    "hands": [
      [
        [
          442,
          342
        ],
        [
          470,
          333
        ],
        [
          496,
          327
        ],
        [
          498,
          315
        ],
        [
          483,
          317
        ],
        [
          475,
          282
        ],
        [
          478,
          255
        ],
        [
          479,
          264
        ],
        [
          478,
          278
        ],
        [
          457,
          279
        ],
        [
          461,
          247
        ],
        [
          464,
          257
        ],
        [
          463,
          272
        ],
        [
          440,
          279
        ],
        [
          444,
          250
        ],
        [
          446,
          256
        ],
        [
          447,
          273
        ],
        [
          423,
          285
        ],
        [
          428,
          262
        ],
        [
          430,
          267
        ],
        [
          432,
          280
        ]
      ]
    ],
    "frame_index": 53
  },
  {
    "hands": [
      [
        [
          442,
          342
        ],
        [
          470,
          333
        ],
        [
          496,
          326
        ],
        [
          498,
          315
        ],
        [
          484,
          317
        ],
        [
          475,
          281
        ],
        [
          478,
          254
        ],
        [
          479,
          264
        ],
        [
          477,
          277
        ],
        [
          457,
          278
        ],
        [
          460,
          246
        ],
        [
          464,
          257
        ],
        [
          463,
          272
        ],
        [
          440,
          279
        ],
        [
          443,
          250
        ],
        [
          446,
          256
        ],
        [
          447,
          274
        ],
        [
          423,
          285
        ],
        [
          428,
          263
        ],
        [
          430,
          267
        ],
        [
          432,
          280
        ]
      ]
    ],
    "frame_index": 54
  },
  {
    "hands": [
      [
        [
          442,
          342
        ],
        [
          470,
          333
        ],
        [
          496,
          326
        ],
        [
          498,
          315
        ],
        [
          484,
          317
        ],
        [
          475,
          281
        ],
        [
          478,
          254
        ],
        [
          479,
          264
        ],
        [
          477,
          277
        ],
        [
          457,
          278
        ],
        [
          460,
          246
        ],
        [
          464,
          258
        ],
        [
          463,
          272
        ],
        [
          441,
          279
        ],
        [
          443,
          250
        ],
        [
          446,
          256
        ],
        [
          447,
          274
        ],
        [
          423,
          285
        ],
        [
          428,
          262
        ],
        [
          430,
          267
        ],
        [
          432,
          280
        ]
      ]
    ],
    "frame_index": 55
  },
  {
    "hands": [
      [
        [
          442,
          342
        ],
        [
          470,
          333
        ],
        [
          496,
          326
        ],
        [
          498,
          315
        ],
        [
          484,
          317
        ],
        [
          475,
          281
        ],
        [
          478,
          254
        ],
        [
          479,
          264
        ],
        [
          477,
          277
        ],
        [
          457,
          278
        ],
        [
          460,
          246
        ],
        [
          464,
          258
        ],
        [
          463,
          272
        ],
        [
          441,
          279
        ],
        [
          443,
          250
        ],
        [
          446,
          256
        ],
        [
          447,
          274
        ],
        [
          423,
          285
        ],
        [
          428,
          262
        ],
        [
          430,
          267
        ],
        [
          432,
          280
        ]
      ]
    ],
    "frame_index": 56
  },
  {
    "hands": [
      [
        [
          442,
          341
        ],
        [
          470,
          332
        ],
        [
          497,
          326
        ],
        [
          498,
          315
        ],
        [
          485,
          316
        ],
        [
          477,
          282
        ],
        [
          478,
          254
        ],
        [
          480,
          264
        ],
        [
          478,
          277
        ],
        [
          458,
          278
        ],
        [
          461,
          246
        ],
        [
          465,
          258
        ],
        [
          464,
          273
        ],
        [
          441,
          278
        ],
        [
          444,
          249
        ],
        [
          447,
          256
        ],
        [
          448,
          274
        ],
        [
          423,
          284
        ],
        [
          428,
          261
        ],
        [
          431,
          266
        ],
        [
          432,
          277
        ]
      ]
    ],
    "frame_index": 57
  },
  {
    "hands": [
      [
        [
          441,
          344
        ],
        [
          471,
          331
        ],
        [
          499,
          318
        ],
        [
          499,
          314
        ],
        [
          490,
          314
        ],
        [
          477,
          283
        ],
        [
          479,
          253
        ],
        [
          480,
          263
        ],
        [
          480,
          275
        ],
        [
          459,
          280
        ],
        [
          462,
          245
        ],
        [
          466,
          258
        ],
        [
          466,
          274
        ],
        [
          442,
          278
        ],
        [
          445,
          248
        ],
        [
          448,
          257
        ],
        [
          450,
          274
        ],
        [
          425,
          282
        ],
        [
          429,
          259
        ],
        [
          432,
          264
        ],
        [
          432,
          274
        ]
      ]
    ],
    "frame_index": 58
  },
  {
    "hands": [
      [
        [
          440,
          344
        ],
        [
          469,
          333
        ],
        [
          495,
          326
        ],
        [
          506,
          313
        ],
        [
          495,
          307
        ],
        [
          478,
          285
        ],
        [
          481,
          252
        ],
        [
          482,
          264
        ],
        [
          481,
          276
        ],
        [
          459,
          281
        ],
        [
          464,
          245
        ],
        [
          468,
          259
        ],
        [
          467,
          274
        ],
        [
          443,
          278
        ],
        [
          447,
          247
        ],
        [
          450,
          257
        ],
        [
          451,
          274
        ],
        [
          425,
          280
        ],
        [
          430,
          256
        ],
        [
          433,
          261
        ],
        [
          435,
          272
        ]
      ]
    ],
    "frame_index": 59
  },
  {
    "hands": [
      [
        [
          439,
          345
        ],
        [
          469,
          335
        ],
        [
          495,
          327
        ],
        [
          508,
          312
        ],
        [
          500,
          301
        ],
        [
          479,
          288
        ],
        [
          484,
          253
        ],
        [
          485,
          266
        ],
        [
          484,
          279
        ],
        [
          458,
          281
        ],
        [
          466,
          246
        ],
        [
          469,
          262
        ],
        [
          468,
          276
        ],
        [
          441,
          278
        ],
        [
          449,
          248
        ],
        [
          453,
          260
        ],
        [
          454,
          277
        ],
        [
          425,
          279
        ],
        [
          429,
          255
        ],
        [
          434,
          261
        ],
        [
          435,
          272
        ]
      ]
    ],
    "frame_index": 60
  },
  {
    "hands": [
      [
        [
          440,
          345
        ],
        [
          467,
          337
        ],
        [
          494,
          331
        ],
        [
          508,
          313
        ],
        [
          504,
          297
        ],
        [
          478,
          291
        ],
        [
          488,
          258
        ],
        [
          489,
          272
        ],
        [
          489,
          286
        ],
        [
          456,
          282
        ],
        [
          468,
          250
        ],
        [
          472,
          267
        ],
        [
          471,
          282
        ],
        [
          440,
          281
        ],
        [
          451,
          250
        ],
        [
          455,
          265
        ],
        [
          457,
          283
        ],
        [
          424,
          282
        ],
        [
          428,
          259
        ],
        [
          434,
          267
        ],
        [
          437,
          280
        ]
      ]
    ],
    "frame_index": 61
  },
  {
    "hands": [
      [
        [
          440,
          345
        ],
        [
          467,
          337
        ],
        [
          494,
          331
        ],
        [
          508,
          313
        ],
        [
          504,
          297
        ],
        [
          478,
          291
        ],
        [
          488,
          258
        ],
        [
          489,
          272
        ],
        [
          489,
          286
        ],
        [
          456,
          282
        ],
        [
          468,
          250
        ],
        [
          472,
          267
        ],
        [
          471,
          282
        ],
        [
          440,
          281
        ],
        [
          451,
          250
        ],
        [
          455,
          265
        ],
        [
          457,
          283
        ],
        [
          424,
          282
        ],
        [
          428,
          259
        ],
        [
          434,
          267
        ],
        [
          437,
          280
        ]
      ]
    ],
    "frame_index": 62
  },
  {
    "hands": [
      [
        [
          440,
          352
        ],
        [
          468,
          342
        ],
        [
          495,
          332
        ],
        [
          509,
          316
        ],
        [
          509,
          299
        ],
        [
          479,
          302
        ],
        [
          493,
          268
        ],
        [
          493,
          286
        ],
        [
          491,
          299
        ],
        [
          460,
          292
        ],
        [
          471,
          258
        ],
        [
          476,
          277
        ],
        [
          474,
          295
        ],
        [
          444,
          290
        ],
        [
          453,
          258
        ],
        [
          458,
          275
        ],
        [
          460,
          293
        ],
        [
          425,
          288
        ],
        [
          429,
          267
        ],
        [
          438,
          276
        ],
        [
          441,
          289
        ]
      ]
    ],
    "frame_index": 63
  },
  {
    "hands": [
      [
        [
          445,
          359
        ],
        [
          471,
          351
        ],
        [
          497,
          340
        ],
        [
          510,
          324
        ],
        [
          514,
          305
        ],
        [
          484,
          318
        ],
        [
          497,
          282
        ],
        [
          497,
          303
        ],
        [
          494,
          314
        ],
        [
          465,
          304
        ],
        [
          477,
          271
        ],
        [
          481,
          294
        ],
        [
          477,
          311
        ],
        [
          445,
          298
        ],
        [
          456,
          273
        ],
        [
          462,
          294
        ],
        [
          463,
          312
        ],
        [
          430,
          298
        ],
        [
          435,
          280
        ],
        [
          444,
          294
        ],
        [
          448,
          311
        ]
      ]
    ],
    "frame_index": 64
  },
  {
    "hands": [
      [
        [
          448,
          368
        ],
        [
          474,
          362
        ],
        [
          500,
          351
        ],
        [
          513,
          335
        ],
        [
          514,
          315
        ],
        [
          495,
          302
        ],
        [
          499,
          296
        ],
        [
          500,
          318
        ],
        [
          499,
          332
        ],
        [
          476,
          300
        ],
        [
          480,
          291
        ],
        [
          485,
          319
        ],
        [
          482,
          336
        ],
        [
          454,
          305
        ],
        [
          460,
          296
        ],
        [
          467,
          318
        ],
        [
          469,
          337
        ],
        [
          432,
          314
        ],
        [
          442,
          303
        ],
        [
          450,
          321
        ],
        [
          454,
          335
        ]
      ]
    ],
    "frame_index": 65
  },
  {
    "hands": [
      [
        [
          450,
          388
        ],
        [
          479,
          384
        ],
        [
          505,
          371
        ],
        [
          517,
          355
        ],
        [
          518,
          338
        ],
        [
          500,
          321
        ],
        [
          503,
          316
        ],
        [
          506,
          340
        ],
        [
          505,
          353
        ],
        [
          480,
          321
        ],
        [
          485,
          313
        ],
        [
          492,
          345
        ],
        [
          492,
          362
        ],
        [
          457,
          327
        ],
        [
          466,
          323
        ],
        [
          475,
          347
        ],
        [
          478,
          366
        ],
        [
          437,
          335
        ],
        [
          449,
          329
        ],
        [
          458,
          349
        ],
        [
          460,
          363
        ]
      ]
    ],
    "frame_index": 66
  },
  {
    "hands": [
      [
        [
          453,
          417
        ],
        [
          472,
          360
        ],
        [
          0,
          0
        ],
        [
          0,
          0
        ],
        [
          0,
          0
        ],
        [
          496,
          341
        ],
        [
          507,
          344
        ],
        [
          511,
          367
        ],
        [
          513,
          383
        ],
        [
          482,
          340
        ],
        [
          491,
          345
        ],
        [
          498,
          378
        ],
        [
          498,
          389
        ],
        [
          468,
          346
        ],
        [
          476,
          362
        ],
        [
          483,
          386
        ],
        [
          485,
          399
        ],
        [
          454,
          358
        ],
        [
          460,
          373
        ],
        [
          466,
          388
        ],
        [
          467,
          399
        ]
      ]
    ],
    "frame_index": 67
  },
  {
    "hands": [
      [
        [
          453,
          416
        ],
        [
          472,
          360
        ],
        [
          0,
          0
        ],
        [
          0,
          0
        ],
        [
          0,
          0
        ],
        [
          496,
          341
        ],
        [
          507,
          344
        ],
        [
          511,
          368
        ],
        [
          513,
          383
        ],
        [
          482,
          340
        ],
        [
          491,
          345
        ],
        [
          498,
          378
        ],
        [
          498,
          389
        ],
        [
          467,
          346
        ],
        [
          476,
          362
        ],
        [
          483,
          387
        ],
        [
          486,
          399
        ],
        [
          453,
          358
        ],
        [
          460,
          373
        ],
        [
          466,
          388
        ],
        [
          467,
          399
        ]
      ]
    ],
    "frame_index": 68
  },
  {
    "hands": [
      [
        [
          460,
          438
        ],
        [
          0,
          0
        ],
        [
          0,
          0
        ],
        [
          0,
          0
        ],
        [
          0,
          0
        ],
        [
          477,
          378
        ],
        [
          0,
          0
        ],
        [
          0,
          0
        ],
        [
          0,
          0
        ],
        [
          474,
          377
        ],
        [
          493,
          395
        ],
        [
          499,
          409
        ],
        [
          0,
          0
        ],
        [
          460,
          384
        ],
        [
          484,
          401
        ],
        [
          492,
          417
        ],
        [
          0,
          0
        ],
        [
          449,
          395
        ],
        [
          468,
          412
        ],
        [
          473,
          425
        ],
        [
          473,
          433
        ]
      ]
    ],
    "frame_index": 69
  },
  {
    "hands": [
      [
        [
          0,
          0
        ],
        [
          489,
          410
        ],
        [
          510,
          424
        ],
        [
          0,
          0
        ],
        [
          0,
          0
        ],
        [
          518,
          416
        ],
        [
          525,
          430
        ],
        [
          527,
          444
        ],
        [
          527,
          453
        ],
        [
          504,
          421
        ],
        [
          513,
          444
        ],
        [
          516,
          459
        ],
        [
          517,
          467
        ],
        [
          487,
          430
        ],
        [
          496,
          446
        ],
        [
          502,
          468
        ],
        [
          504,
          474
        ],
        [
          468,
          444
        ],
        [
          483,
          462
        ],
        [
          488,
          473
        ],
        [
          491,
          478
        ]
      ]
    ],
    "frame_index": 70
  }
]