[
  {
    "hands": [
      [
        [
          107,
          479
        ],
        [
          128,
          490
        ],
        [
          147,
          504
        ],
        [
          163,
          520
        ],
        [
          182,
          536
        ],
        [
          118,
          519
        ],
        [
          124,
          521
        ],
        [
          124,
          524
        ],
        [
          16,
          532
        ],
        [
          92,
          525
        ],
        [
          0,
          0
        ],
        [
          0,
          0
        ],
        [
          0,
          0
        ],
        [
          0,
          0
        ],
        [
          0,
          0
        ],
        [
          0,
          0
        ],
        [
          0,
          0
        ],
        [
          0,
          0
        ],
        [
          0,
          0
        ],
        [
          0,
          0
        ],
        [
          0,
          0
        ]
      ]
    ],
    "frame_index": 0
  },
  {
    "hands": [
      [
        [
          107,
          508
        ],
        [
          114,
          500
        ],
        [
          125,
          526
        ],
        [
          88,
          460
        ],
        [
          76,
          440
        ],
        [
          0,
          0
        ],
        [
          37,
          492
        ],
        [
          22,
          495
        ],
        [
          9,
          495
        ],
        [
          0,
          0
        ],
        [
          0,
          0
        ],
        [
          0,
          0
        ],
        [
          0,
          0
        ],
        [
          35,
          518
        ],
        [
          0,
          0
        ],
        [
          0,
          0
        ],
        [
          0,
          0
        ],
        [
          37,
          528
        ],
        [
          0,
          0
        ],
        [
          0,
          0
        ],
        [
          0,
          0
        ]
      ]
    ],
    "frame_index": 1
  },
  {
    "hands": [
      [
        [
          98,
          504
        ],
        [
          89,
          481
        ],
        [
          75,
          451
        ],
        [
          64,
          420
        ],
        [
          50,
          393
        ],
        [
          0,
          0
        ],
        [
          0,
          0
        ],
        [
          0,
          0
        ],
        [
          0,
          0
        ],
        [
          0,
          0
        ],
        [
          0,
          0
        ],
        [
          0,
          0
        ],
        [
          0,
          0
        ],
        [
          0,
          0
        ],
        [
          0,
          0
        ],
        [
          0,
          0
        ],
        [
          0,
          0
        ],
        [
          0,
          0
        ],
        [
          0,
          0
        ],
        [
          0,
          0
        ],
        [
          0,
          0
        ]
      ]
    ],
    "frame_index": 2
  },
  {
    "hands": [
      [
        [
          87,
          476
        ],
        [
          73,
          444
        ],
        [
          69,
          413
        ],
        [
          58,
          368
        ],
        [
          52,
          340
        ],
        [
          0,
          0
        ],
        [
          0,
          0
        ],
        [
          0,
          0
        ],
        [
          0,
          0
        ],
        [
          0,
          0
        ],
        [
          0,
          0
        ],
        [
          0,
          0
        ],
        [
          0,
          0
        ],
        [
          0,
          0
        ],
        [
          0,
          0
        ],
        [
          0,
          0
        ],
        [
          0,
          0
        ],
        [
          0,
          0
        ],
        [
          0,
          0
        ],
        [
          0,
          0
        ],
        [
          0,
          0
        ]
      ]
    ],
    "frame_index": 3
  },
  {
    "hands": [
      [
        [
          82,
          466
        ],
        [
          102,
          440
        ],
        [
          123,
          430
        ],
        [
          124,
          429
        ],
        [
          124,
          419
        ],
        [
          0,
          0
        ],
        [
          0,
          0
        ],
        [
          0,
          0
        ],
        [
          0,
          0
        ],
        [
          0,
          0
        ],
        [
          0,
          0
        ],
        [
          0,
          0
        ],
        [
          0,
          0
        ],
        [
          0,
          0
        ],
        [
          0,
          0
        ],
        [
          0,
          0
        ],
        [
          0,
          0
        ],
        [
          0,
          0
        ],
        [
          0,
          0
        ],
        [
          0,
          0
        ],
        [
          0,
          0
        ]
      ]
    ],
    "frame_index": 4
  },
  {
    "hands": [
      [
        [
          80,
          441
        ],
        [
          100,
          403
        ],
        [
          115,
          385
        ],
        [
          133,
          381
        ],
        [
          150,
          363
        ],
        [
          68,
          352
        ],
        [
          75,
          335
        ],
        [
          67,
          294
        ],
        [
          71,
          258
        ],
        [
          41,
          378
        ],
        [
          0,
          0
        ],
        [
          0,
          0
        ],
        [
          0,
          0
        ],
        [
          53,
          410
        ],
        [
          0,
          0
        ],
        [
          0,
          0
        ],
        [
          0,
          0
        ],
        [
          72,
          427
        ],
        [
          0,
          0
        ],
        [
          74,
          427
        ],
        [
          0,
          0
        ]
      ]
    ],
    "frame_index": 5
  },
  {
    "hands": [
      [
        [
          77,
          406
        ],
        [
          105,
          369
        ],
        [
          132,
          351
        ],
        [
          154,
          341
        ],
        [
          172,
          326
        ],
        [
          90,
          312
        ],
        [
          72,
          268
        ],
        [
          75,
          244
        ],
        [
          89,
          222
        ],
        [
          72,
          331
        ],
        [
          0,
          0
        ],
        [
          0,
          0
        ],
        [
          0,
          0
        ],
        [
          0,
          0
        ],
        [
          0,
          0
        ],
        [
          0,
          0
        ],
        [
          0,
          0
        ],
        [
          0,
          0
        ],
        [
          68,
          262
        ],
        [
          73,
          239
        ],
        [
          91,
          222
        ]
      ]
    ],
    "frame_index": 6
  },
  {
    "hands": [
      [
        [
          79,
          386
        ],
        [
          113,
          348
        ],
        [
          149,
          322
        ],
        [
          174,
          315
        ],
        [
          189,
          304
        ],
        [
          87,
          287
        ],
        [
          79,
          241
        ],
        [
          89,
          216
        ],
        [
          110,
          199
        ],
        [
          77,
          302
        ],
        [
          105,
          281
        ],
        [
          143,
          289
        ],
        [
          0,
          0
        ],
        [
          79,
          322
        ],
        [
          103,
          304
        ],
        [
          119,
          303
        ],
        [
          140,
          323
        ],
        [
          89,
          342
        ],
        [
          98,
          335
        ],
        [
          111,
          334
        ],
        [
          112,
          199
        ]
      ]
    ],
    "frame_index": 7
  },
  {
    "hands": [
      [
        [
          84,
          366
        ],
        [
          90,
          325
        ],
        [
          104,
          293
        ],
        [
          0,
          0
        ],
        [
          0,
          0
        ],
        [
          94,
          272
        ],
        [
          92,
          223
        ],
        [
          105,
          198
        ],
        [
          130,
          185
        ],
        [
          93,
          285
        ],
        [
          132,
          256
        ],
        [
          167,
          269
        ],
        [
          200,
          286
        ],
        [
          98,
          304
        ],
        [
          134,
          280
        ],
        [
          170,
          289
        ],
        [
          198,
          293
        ],
        [
          108,
          321
        ],
        [
          141,
          304
        ],
        [
          163,
          308
        ],
        [
          182,
          308
        ]
      ]
    ],
    "frame_index": 8
  },
  {
    "hands": [
      [
        [
          91,
          345
        ],
        [
          100,
          307
        ],
        [
          122,
          278
        ],
        [
          0,
          0
        ],
        [
          0,
          0
        ],
        [
          110,
          260
        ],
        [
          107,
          209
        ],
        [
          123,
          186
        ],
        [
          149,
          177
        ],
        [
          110,
          276
        ],
        [
          151,
          246
        ],
        [
          185,
          261
        ],
        [
          200,
          276
        ],
        [
          116,
          291
        ],
        [
          155,
          270
        ],
        [
          187,
          281
        ],
        [
          210,
          289
        ],
        [
          123,
          308
        ],
        [
          160,
          295
        ],
        [
          181,
          299
        ],
        [
          195,
          301
        ]
      ]
    ],
    "frame_index": 9
  },
  {
    "hands": [],
    "frame_index": 10
  },
  {
    "hands": [
      [
        [
          99,
          337
        ],
        [
          116,
          294
        ],
        [
          135,
          259
        ],
        [
          157,
          255
        ],
        [
          173,
          227
        ],
        [
          133,
          248
        ],
        [
          131,
          198
        ],
        [
          150,
          177
        ],
        [
          179,
          173
        ],
        [
          135,
          267
        ],
        [
          181,
          240
        ],
        [
          208,
          257
        ],
        [
          221,
          280
        ],
        [
          141,
          285
        ],
        [
          184,
          262
        ],
        [
          209,
          276
        ],
        [
          217,
          289
        ],
        [
          149,
          303
        ],
        [
          183,
          287
        ],
        [
          201,
          293
        ],
        [
          208,
          300
        ]
      ]
    ],
    "frame_index": 11
  },
  {
    "hands": [],
    "frame_index": 12
  },
  {
    "hands": [],
    "frame_index": 13
  },
  {
    "hands": [
      [
        [
          108,
          346
        ],
        [
          123,
          305
        ],
        [
          142,
          266
        ],
        [
          170,
          259
        ],
        [
          196,
          267
        ],
        [
          145,
          253
        ],
        [
          146,
          204
        ],
        [
          167,
          186
        ],
        [
          195,
          188
        ],
        [
          149,
          269
        ],
        [
          197,
          248
        ],
        [
          221,
          265
        ],
        [
          229,
          285
        ],
        [
          155,
          284
        ],
        [
          202,
          269
        ],
        [
          221,
          286
        ],
        [
          226,
          297
        ],
        [
          164,
          303
        ],
        [
          198,
          294
        ],
        [
          212,
          303
        ],
        [
          212,
          313
        ]
      ]
    ],
    "frame_index": 14
  },
  {
    "hands": [
      [
        [
          109,
          357
        ],
        [
          122,
          317
        ],
        [
          143,
          274
        ],
        [
          171,
          266
        ],
        [
          200,
          277
        ],
        [
          145,
          263
        ],
        [
          147,
          211
        ],
        [
          170,
          193
        ],
        [
          197,
          198
        ],
        [
          150,
          277
        ],
        [
          199,
          257
        ],
        [
          224,
          275
        ],
        [
          231,
          294
        ],
        [
          157,
          293
        ],
        [
          205,
          280
        ],
        [
          225,
          296
        ],
        [
          226,
          309
        ],
        [
          168,
          311
        ],
        [
          202,
          305
        ],
        [
          214,
          314
        ],
        [
          213,
          323
        ]
      ]
    ],
    "frame_index": 15
  },
  {
    "hands": [
      [
        [
          111,
          365
        ],
        [
          123,
          327
        ],
        [
          143,
          284
        ],
        [
          172,
          277
        ],
        [
          0,
          0
        ],
        [
          147,
          272
        ],
        [
          149,
          220
        ],
        [
          172,
          203
        ],
        [
          198,
          208
        ],
        [
          151,
          287
        ],
        [
          202,
          268
        ],
        [
          225,
          286
        ],
        [
          231,
          304
        ],
        [
          159,
          303
        ],
        [
          208,
          292
        ],
        [
          227,
          307
        ],
        [
          226,
          318
        ],
        [
          170,
          322
        ],
        [
          204,
          317
        ],
        [
          216,
          325
        ],
        [
          214,
          333
        ]
      ]
    ],
    "frame_index": 16
  },
  {
    "hands": [
      [
        [
          112,
          379
        ],
        [
          122,
          339
        ],
        [
          140,
          298
        ],
        [
          172,
          286
        ],
        [
          0,
          0
        ],
        [
          147,
          282
        ],
        [
          148,
          230
        ],
        [
          171,
          212
        ],
        [
          198,
          217
        ],
        [
          152,
          296
        ],
        [
          203,
          280
        ],
        [
          226,
          296
        ],
        [
          232,
          314
        ],
        [
          160,
          314
        ],
        [
          209,
          302
        ],
        [
          228,
          316
        ],
        [
          229,
          327
        ],
        [
          172,
          333
        ],
        [
          204,
          327
        ],
        [
          216,
          334
        ],
        [
          216,
          342
        ]
      ]
    ],
    "frame_index": 17
  },
  {
    "hands": [
      [
        [
          113,
          385
        ],
        [
          123,
          345
        ],
        [
          144,
          304
        ],
        [
          172,
          298
        ],
        [
          232,
          324
        ],
        [
          146,
          292
        ],
        [
          147,
          237
        ],
        [
          170,
          220
        ],
        [
          196,
          224
        ],
        [
          150,
          306
        ],
        [
          202,
          289
        ],
        [
          227,
          305
        ],
        [
          233,
          323
        ],
        [
          159,
          324
        ],
        [
          209,
          312
        ],
        [
          227,
          325
        ],
        [
          228,
          335
        ],
        [
          171,
          344
        ],
        [
          205,
          337
        ],
        [
          216,
          343
        ],
        [
          217,
          352
        ]
      ]
    ],
    "frame_index": 18
  },
  {
    "hands": [
      [
        [
          113,
          389
        ],
        [
          122,
          350
        ],
        [
          140,
          308
        ],
        [
          169,
          301
        ],
        [
          232,
          330
        ],
        [
          144,
          298
        ],
        [
          145,
          244
        ],
        [
          167,
          227
        ],
        [
          194,
          230
        ],
        [
          149,
          312
        ],
        [
          201,
          296
        ],
        [
          225,
          309
        ],
        [
          233,
          328
        ],
        [
          157,
          330
        ],
        [
          208,
          318
        ],
        [
          226,
          329
        ],
        [
          227,
          339
        ],
        [
          170,
          348
        ],
        [
          205,
          341
        ],
        [
          216,
          347
        ],
        [
          216,
          355
        ]
      ]
    ],
    "frame_index": 19
  },
  {
    "hands": [
      [
        [
          110,
          393
        ],
        [
          120,
          354
        ],
        [
          137,
          314
        ],
        [
          168,
          308
        ],
        [
          230,
          332
        ],
        [
          142,
          301
        ],
        [
          143,
          248
        ],
        [
          165,
          230
        ],
        [
          191,
          233
        ],
        [
          147,
          315
        ],
        [
          200,
          299
        ],
        [
          224,
          313
        ],
        [
          232,
          331
        ],
        [
          156,
          334
        ],
        [
          208,
          322
        ],
        [
          225,
          333
        ],
        [
          225,
          342
        ],
        [
          168,
          353
        ],
        [
          203,
          345
        ],
        [
          215,
          350
        ],
        [
          215,
          357
        ]
      ]
    ],
    "frame_index": 20
  },
  {
    "hands": [
      [
        [
          110,
          396
        ],
        [
          119,
          357
        ],
        [
          136,
          316
        ],
        [
          167,
          311
        ],
        [
          229,
          333
        ],
        [
          142,
          303
        ],
        [
          141,
          249
        ],
        [
          163,
          232
        ],
        [
          190,
          233
        ],
        [
          146,
          318
        ],
        [
          199,
          301
        ],
        [
          223,
          313
        ],
        [
          231,
          331
        ],
        [
          154,
          337
        ],
        [
          207,
          323
        ],
        [
          224,
          333
        ],
        [
          225,
          343
        ],
        [
          166,
          356
        ],
        [
          202,
          345
        ],
        [
          214,
          350
        ],
        [
          215,
          357
        ]
      ]
    ],
    "frame_index": 21
  },
  {
    "hands": [
      [
        [
          110,
          394
        ],
        [
          119,
          356
        ],
        [
          136,
          316
        ],
        [
          166,
          309
        ],
        [
          229,
          333
        ],
        [
          141,
          303
        ],
        [
          140,
          250
        ],
        [
          162,
          232
        ],
        [
          190,
          233
        ],
        [
          146,
          319
        ],
        [
          198,
          301
        ],
        [
          223,
          314
        ],
        [
          231,
          332
        ],
        [
          154,
          337
        ],
        [
          206,
          323
        ],
        [
          224,
          334
        ],
        [
          224,
          343
        ],
        [
          166,
          356
        ],
        [
          203,
          346
        ],
        [
          214,
          351
        ],
        [
          214,
          358
        ]
      ]
    ],
    "frame_index": 22
  },
  {
    "hands": [
      [
        [
          110,
          394
        ],
        [
          118,
          356
        ],
        [
          136,
          316
        ],
        [
          166,
          309
        ],
        [
          229,
          333
        ],
        [
          141,
          303
        ],
        [
          141,
          249
        ],
        [
          163,
          232
        ],
        [
          190,
          233
        ],
        [
          146,
          318
        ],
        [
          198,
          301
        ],
        [
          223,
          313
        ],
        [
          231,
          331
        ],
        [
          154,
          336
        ],
        [
          206,
          322
        ],
        [
          224,
          333
        ],
        [
          224,
          343
        ],
        [
          166,
          355
        ],
        [
          202,
          345
        ],
        [
          214,
          350
        ],
        [
          215,
          358
        ]
      ]
    ],
    "frame_index": 23
  },
  {
    "hands": [
      [
        [
          110,
          393
        ],
        [
          118,
          355
        ],
        [
          135,
          315
        ],
        [
          166,
          306
        ],
        [
          229,
          332
        ],
        [
          141,
          302
        ],
        [
          142,
          248
        ],
        [
          164,
          232
        ],
        [
          191,
          233
        ],
        [
          147,
          317
        ],
        [
          198,
          300
        ],
        [
          223,
          312
        ],
        [
          231,
          331
        ],
        [
          154,
          335
        ],
        [
          206,
          321
        ],
        [
          224,
          332
        ],
        [
          225,
          343
        ],
        [
          166,
          354
        ],
        [
          202,
          343
        ],
        [
          214,
          349
        ],
        [
          215,
          357
        ]
      ]
    ],
    "frame_index": 24
  },
  {
    "hands": [
      [
        [
          109,
          394
        ],
        [
          118,
          355
        ],
        [
          136,
          315
        ],
        [
          166,
          308
        ],
        [
          229,
          332
        ],
        [
          141,
          301
        ],
        [
          141,
          247
        ],
        [
          164,
          231
        ],
        [
          191,
          233
        ],
        [
          146,
          317
        ],
        [
          198,
          299
        ],
        [
          223,
          311
        ],
        [
          231,
          330
        ],
        [
          154,
          334
        ],
        [
          206,
          320
        ],
        [
          224,
          332
        ],
        [
          225,
          343
        ],
        [
          166,
          353
        ],
        [
          202,
          343
        ],
        [
          214,
          349
        ],
        [
          215,
          357
        ]
      ]
    ],
    "frame_index": 25
  },
  {
    "hands": [
      [
        [
          109,
          392
        ],
        [
          120,
          353
        ],
        [
          136,
          313
        ],
        [
          166,
          308
        ],
        [
          229,
          332
        ],
        [
          141,
          301
        ],
        [
          141,
          247
        ],
        [
          164,
          230
        ],
        [
          191,
          232
        ],
        [
          147,
          317
        ],
        [
          197,
          298
        ],
        [
          222,
          312
        ],
        [
          229,
          331
        ],
        [
          154,
          334
        ],
        [
          205,
          320
        ],
        [
          223,
          333
        ],
        [
          222,
          343
        ],
        [
          165,
          352
        ],
        [
          201,
          344
        ],
        [
          214,
          349
        ],
        [
          214,
          357
        ]
      ]
    ],
    "frame_index": 26
  },
  {
    "hands": [
      [
        [
          110,
          391
        ],
        [
          120,
          352
        ],
        [
          136,
          312
        ],
        [
          166,
          308
        ],
        [
          228,
          331
        ],
        [
          141,
          301
        ],
        [
          141,
          246
        ],
        [
          164,
          229
        ],
        [
          190,
          232
        ],
        [
          146,
          317
        ],
        [
          196,
          298
        ],
        [
          221,
          312
        ],
        [
          228,
          329
        ],
        [
          154,
          333
        ],
        [
          204,
          319
        ],
        [
          222,
          332
        ],
        [
          223,
          341
        ],
        [
          165,
          352
        ],
        [
          201,
          344
        ],
        [
          214,
          349
        ],
        [
          214,
          357
        ]
      ]
    ],
    "frame_index": 27
  },
  {
    "hands": [
      [
        [
          108,
          391
        ],
        [
          120,
          352
        ],
        [
          136,
          313
        ],
        [
          166,
          309
        ],
        [
          228,
          331
        ],
        [
          141,
          301
        ],
        [
          142,
          246
        ],
        [
          164,
          230
        ],
        [
          191,
          231
        ],
        [
          146,
          317
        ],
        [
          196,
          298
        ],
        [
          221,
          311
        ],
        [
          229,
          329
        ],
        [
          153,
          333
        ],
        [
          204,
          319
        ],
        [
          222,
          332
        ],
        [
          222,
          342
        ],
        [
          165,
          350
        ],
        [
          200,
          342
        ],
        [
          213,
          349
        ],
        [
          213,
          356
        ]
      ]
    ],
    "frame_index": 28
  },
  {
    "hands": [
      [
        [
          108,
          392
        ],
        [
          120,
          351
        ],
        [
          137,
          311
        ],
        [
          166,
          309
        ],
        [
          226,
          331
        ],
        [
          141,
          299
        ],
        [
          141,
          245
        ],
        [
          164,
          229
        ],
        [
          190,
          231
        ],
        [
          145,
          315
        ],
        [
          196,
          298
        ],
        [
          220,
          311
        ],
        [
          228,
          330
        ],
        [
          153,
          332
        ],
        [
          203,
          318
        ],
        [
          221,
          332
        ],
        [
          221,
          342
        ],
        [
          164,
          349
        ],
        [
          199,
          341
        ],
        [
          212,
          348
        ],
        [
          212,
          356
        ]
      ]
    ],
    "frame_index": 29
  },
  {
    "hands": [
      [
        [
          108,
          389
        ],
        [
          120,
          350
        ],
        [
          136,
          310
        ],
        [
          166,
          309
        ],
        [
          223,
          331
        ],
        [
          140,
          300
        ],
        [
          140,
          246
        ],
        [
          163,
          229
        ],
        [
          190,
          231
        ],
        [
          145,
          316
        ],
        [
          195,
          298
        ],
        [
          220,
          312
        ],
        [
          226,
          331
        ],
        [
          153,
          333
        ],
        [
          202,
          319
        ],
        [
          220,
          332
        ],
        [
          220,
          342
        ],
        [
          164,
          350
        ],
        [
          199,
          342
        ],
        [
          211,
          349
        ],
        [
          211,
          356
        ]
      ]
    ],
    "frame_index": 30
  },
  {
    "hands": [
      [
        [
          107,
          392
        ],
        [
          119,
          352
        ],
        [
          136,
          311
        ],
        [
          163,
          306
        ],
        [
          225,
          331
        ],
        [
          138,
          300
        ],
        [
          139,
          247
        ],
        [
          162,
          229
        ],
        [
          188,
          232
        ],
        [
          144,
          316
        ],
        [
          192,
          297
        ],
        [
          218,
          311
        ],
        [
          225,
          327
        ],
        [
          152,
          332
        ],
        [
          201,
          319
        ],
        [
          220,
          330
        ],
        [
          221,
          339
        ],
        [
          164,
          350
        ],
        [
          197,
          343
        ],
        [
          210,
          349
        ],
        [
          212,
          356
        ]
      ]
    ],
    "frame_index": 31
  },
  {
    "hands": [
      [
        [
          106,
          392
        ],
        [
          116,
          353
        ],
        [
          131,
          311
        ],
        [
          160,
          305
        ],
        [
          224,
          329
        ],
        [
          135,
          300
        ],
        [
          138,
          246
        ],
        [
          162,
          230
        ],
        [
          189,
          232
        ],
        [
          141,
          314
        ],
        [
          190,
          296
        ],
        [
          216,
          310
        ],
        [
          226,
          328
        ],
        [
          148,
          331
        ],
        [
          198,
          317
        ],
        [
          218,
          330
        ],
        [
          219,
          340
        ],
        [
          160,
          348
        ],
        [
          195,
          341
        ],
        [
          209,
          347
        ],
        [
          211,
          354
        ]
      ]
    ],
    "frame_index": 32
  },
  {
    "hands": [
      [
        [
          106,
          394
        ],
        [
          116,
          353
        ],
        [
          132,
          313
        ],
        [
          160,
          309
        ],
        [
          223,
          329
        ],
        [
          134,
          300
        ],
        [
          141,
          249
        ],
        [
          167,
          235
        ],
        [
          194,
          238
        ],
        [
          136,
          316
        ],
        [
          187,
          295
        ],
        [
          214,
          310
        ],
        [
          223,
          329
        ],
        [
          145,
          335
        ],
        [
          195,
          318
        ],
        [
          215,
          331
        ],
        [
          217,
          342
        ],
        [
          157,
          353
        ],
        [
          193,
          343
        ],
        [
          209,
          348
        ],
        [
          211,
          355
        ]
      ]
    ],
    "frame_index": 33
  },
  {
    "hands": [
      [
        [
          104,
          407
        ],
        [
          119,
          361
        ],
        [
          140,
          317
        ],
        [
          0,
          0
        ],
        [
          225,
          336
        ],
        [
          135,
          302
        ],
        [
          153,
          258
        ],
        [
          180,
          250
        ],
        [
          205,
          255
        ],
        [
          137,
          321
        ],
        [
          184,
          300
        ],
        [
          213,
          315
        ],
        [
          228,
          334
        ],
        [
          145,
          343
        ],
        [
          193,
          324
        ],
        [
          216,
          336
        ],
        [
          221,
          349
        ],
        [
          157,
          363
        ],
        [
          194,
          349
        ],
        [
          209,
          354
        ],
        [
          214,
          359
        ]
      ]
    ],
    "frame_index": 34
  },
  {
    "hands": [
      [
        [
          104,
          423
        ],
        [
          123,
          378
        ],
        [
          145,
          331
        ],
        [
          0,
          0
        ],
        [
          0,
          0
        ],
        [
          141,
          318
        ],
        [
          169,
          280
        ],
        [
          199,
          278
        ],
        [
          222,
          286
        ],
        [
          143,
          338
        ],
        [
          191,
          318
        ],
        [
          217,
          333
        ],
        [
          231,
          347
        ],
        [
          149,
          361
        ],
        [
          198,
          343
        ],
        [
          219,
          355
        ],
        [
          224,
          365
        ],
        [
          162,
          383
        ],
        [
          197,
          369
        ],
        [
          213,
          373
        ],
        [
          216,
          377
        ]
      ]
    ],
    "frame_index": 35
  },
  {
    "hands": [
      [
        [
          108,
          439
        ],
        [
          133,
          388
        ],
        [
          153,
          350
        ],
        [
          196,
          329
        ],
        [
          0,
          0
        ],
        [
          147,
          338
        ],
        [
          187,
          308
        ],
        [
          223,
          315
        ],
        [
          237,
          329
        ],
        [
          150,
          359
        ],
        [
          205,
          343
        ],
        [
          230,
          358
        ],
        [
          232,
          372
        ],
        [
          155,
          385
        ],
        [
          207,
          369
        ],
        [
          226,
          381
        ],
        [
          231,
          390
        ],
        [
          165,
          409
        ],
        [
          204,
          397
        ],
        [
          217,
          401
        ],
        [
          224,
          406
        ]
      ]
    ],
    "frame_index": 36
  },
  {
    "hands": [
      [
        [
          113,
          466
        ],
        [
          130,
          422
        ],
        [
          156,
          380
        ],
        [
          197,
          361
        ],
        [
          227,
          368
        ],
        [
          152,
          369
        ],
        [
          199,
          342
        ],
        [
          232,
          350
        ],
        [
          240,
          365
        ],
        [
          158,
          392
        ],
        [
          217,
          380
        ],
        [
          240,
          387
        ],
        [
          243,
          394
        ],
        [
          163,
          419
        ],
        [
          216,
          406
        ],
        [
          236,
          411
        ],
        [
          238,
          414
        ],
        [
          171,
          444
        ],
        [
          212,
          431
        ],
        [
          223,
          433
        ],
        [
          226,
          436
        ]
      ]
    ],
    "frame_index": 37
  },
  {
    "hands": [
      [
        [
          122,
          497
        ],
        [
          111,
          491
        ],
        [
          97,
          489
        ],
        [
          89,
          487
        ],
        [
          85,
          490
        ],
        [
          163,
          409
        ],
        [
          206,
          388
        ],
        [
          241,
          395
        ],
        [
          250,
          400
        ],
        [
          167,
          436
        ],
        [
          214,
          422
        ],
        [
          235,
          419
        ],
        [
          237,
          424
        ],
        [
          173,
          460
        ],
        [
          218,
          454
        ],
        [
          240,
          444
        ],
        [
          238,
          440
        ],
        [
          183,
          482
        ],
        [
          218,
          476
        ],
        [
          232,
          468
        ],
        [
          245,
          455
        ]
      ]
    ],
    "frame_index": 38
  },
  {
    "hands": [],
    "frame_index": 39
  },
  {
    "hands": [],
    "frame_index": 40
  },
  {
    "hands": [],
    "frame_index": 41
  },
  {
    "hands": [],
    "frame_index": 42
  },
  {
    "hands": [],
    "frame_index": 43
  }
]